steamed_hams/__init__.py
steamed_hams/__main__.py
steamed_hams/base.py
steamed_hams/cli.py
steamed_hams-0.1.0.dist-info/LICENSE
steamed_hams-0.1.0.dist-info/METADATA
steamed_hams-0.1.0.dist-info/WHEEL
steamed_hams-0.1.0.dist-info/entry_points.txt
steamed_hams-0.1.0.dist-info/top_level.txt
steamed_hams-0.1.0.dist-info/RECORD
