Metadata-Version: 2.1
Name: steamed-hams
Version: 0.1.0
Summary: Awesome steamed_hams created by unforgettable-luncheon
Home-page: https://github.com/unforgettable-luncheon/steamed-hams/
Author: unforgettable-luncheon
License-File: LICENSE
Provides-Extra: test
Requires-Dist: pytest ; extra == 'test'
Requires-Dist: coverage ; extra == 'test'
Requires-Dist: flake8 ; extra == 'test'
Requires-Dist: black ; extra == 'test'
Requires-Dist: isort ; extra == 'test'
Requires-Dist: pytest-cov ; extra == 'test'
Requires-Dist: codecov ; extra == 'test'
Requires-Dist: mypy ; extra == 'test'
Requires-Dist: gitchangelog ; extra == 'test'
Requires-Dist: mkdocs ; extra == 'test'
